py_gf_auto_doc/__main__.py
py_gf_auto_doc/doc_gen.py
py_gf_auto_doc-0.1.2.dist-info/LICENSE
py_gf_auto_doc-0.1.2.dist-info/METADATA
py_gf_auto_doc-0.1.2.dist-info/WHEEL
py_gf_auto_doc-0.1.2.dist-info/top_level.txt
py_gf_auto_doc-0.1.2.dist-info/RECORD
