Metadata-Version: 2.1
Name: py_gf_auto_doc
Version: 0.1.2
Summary: Auto doc generator for GitFlic book
Author-email: Vladimir Chistov <wchistow@yandex.ru>
Project-URL: Homepage, https://gitflic.ru/project/wchistow/py-gf-auto-doc
Project-URL: Bug Tracker, https://gitflic.ru/project/wchistow/py-gf-auto-doc/issue
Classifier: Programming Language :: Python :: 3
Classifier: License :: OSI Approved :: MIT License
Classifier: Operating System :: OS Independent
Requires-Python: >=3.10
License-File: LICENSE
